redisloghandler.py
setup.py
redis_loghandler.egg-info/PKG-INFO
redis_loghandler.egg-info/SOURCES.txt
redis_loghandler.egg-info/dependency_links.txt
redis_loghandler.egg-info/requires.txt
redis_loghandler.egg-info/top_level.txt