Metadata-Version: 1.0
Name: redis-loghandler
Version: 0.2
Summary: Redis logging handler
Home-page: http://www.quadloops.com
Author: Ashwin Rajeev
Author-email: ashwin@quadloops.com
License: UNKNOWN
Platform: UNKNOWN
